hdev/__init__.py
hdev/cmd.py
hdev/configuration.py
hdev/cookie_cutter.py
hdev/jinja_env.py
hdev/shell.py
hdev/tox_cmd.py
hdev/command/__init__.py
hdev/command/alembic.py
hdev/command/config.py
hdev/command/install_python.py
hdev/command/python_version.py
hdev/command/sub_command.py
hdev/command/template.py
hdev/command/clean/__init__.py
hdev/command/clean/_lazy.py
hdev/command/deps/__init__.py
hdev/command/deps/_lazy.py
hdev/command/requirements/__init__.py
hdev/command/requirements/_lazy.py
hdev/command/run/__init__.py
hdev/command/run/_lazy.py
hdev/model/__init__.py
hdev/model/project.py
hdev/pyenv/__init__.py
hdev/pyenv/pyenv.py
hdev/pyenv/python_versions.py
hdev/pyenv/version_file.py
hdev/requirements/__init__.py
hdev/requirements/compile.py
hdev/requirements/graph.py
hdev/requirements/package.py
hdev/requirements/parse.py
hdev/requirements/pypi_api.py
hdev/requirements/requirements_file.py
hdev/requirements/setup_file.py
hdev/requirements/tree.py
hdev/resources/__init__.py
hdev/resources/bin/__init__.py
hdev/resources/bin/clean_branches.sh
hdev/resources/data/__init__.py
hdev/resources/data/library_usage.csv
hdev/resources/data/packages.json
hdev/resources/requirements/__init__.py
hdev/resources/templates/dep_command.txt.jinja2
hdev/resources/templates/dep_graph.dot.jinja2
hdev-0.1.18.dist-info/LICENSE
hdev-0.1.18.dist-info/METADATA
hdev-0.1.18.dist-info/WHEEL
hdev-0.1.18.dist-info/entry_points.txt
hdev-0.1.18.dist-info/top_level.txt
hdev-0.1.18.dist-info/RECORD
