Metadata-Version: 2.1
Name: hdev
Version: 0.1.18
Summary: CLI for the Hypothesis development environment
Home-page: https://web.hypothes.is/
Author: Hypothesis Engineering Team
Author-email: eng@list.hypothes.is
Maintainer: Hypothesis Engineering Team
Maintainer-email: eng@list.hypothes.is
License: License :: OSI Approved :: BSD License
Project-URL: Source, https://github.com/hypothesis/hdev
Platform: Operating System :: OS Independent
Classifier: Development Status :: 2 - Pre-Alpha
Classifier: Programming Language :: Python :: 3.8
Classifier: Programming Language :: Python :: 3.9
Requires-Dist: cookiecutter
Requires-Dist: diskcache
Requires-Dist: importlib-resources
Requires-Dist: jinja2
Requires-Dist: toml
Requires-Dist: tox
Provides-Extra: tests
Requires-Dist: cookiecutter ; extra == 'tests'
Requires-Dist: coverage ; extra == 'tests'
Requires-Dist: diskcache ; extra == 'tests'
Requires-Dist: h-matchers ; extra == 'tests'
Requires-Dist: importlib-resources ; extra == 'tests'
Requires-Dist: jinja2 ; extra == 'tests'
Requires-Dist: pytest ; extra == 'tests'
Requires-Dist: toml ; extra == 'tests'
Requires-Dist: tox ; extra == 'tests'
